<?xml version="1.0" encoding="UTF-8"?>
<struct type="complexStruct">
	<complexType name="futBscRejTakUpTrnRequestT">
		<sequence>
			<element type="char" name="membClgIdCodTo" size="5"/>
			<element type="char" name="membExchIdCodTo" size="5"/>
			<element type="futCntrIdGrpT" name="futCntrIdGrp"/>
			<element type="char" name="trnDat" size="8"/>
			<element type="char" name="ordrNo" size="9"/>
			<element type="char" name="trnIdNo" size="6"/>
			<element type="trnIdSfxKeyGrpT" name="trnIdSfxKeyGrp"/>
			<element type="char" name="buyCod"/>
			<element type="char" name="dateLstUpdDat" size="18"/>
		</sequence>
	</complexType>
	<complexType name="futRejTakUpTrnRequestT">
		<sequence>
			<element type="dataHeaderT" name="header"/>
			<element type="futBscRejTakUpTrnRequestT" name="basic"/>
		</sequence>
	</complexType>
	<complexType name="futBscRejTakUpTrnResponseT">
		<sequence>
			<element type="char" name="gutSts"/>
			<element type="char" name="dateLstUpdDat" size="18"/>
		</sequence>
	</complexType>
	<complexType name="futRejTakUpTrnResponseT">
		<sequence>
			<element type="dataHeaderT" name="header"/>
			<element type="futBscRejTakUpTrnResponseT" name="basic"/>
		</sequence>
	</complexType>
	<complexType name="optBscRejTakUpTrnRequestT">
		<sequence>
			<element type="char" name="membClgIdCodTo" size="5"/>
			<element type="char" name="membExchIdCodTo" size="5"/>
			<element type="optCntrIdGrpT" name="optCntrIdGrp"/>
			<element type="char" name="trnDat" size="8"/>
			<element type="char" name="ordrNo" size="9"/>
			<element type="char" name="trnIdNo" size="6"/>
			<element type="trnIdSfxKeyGrpT" name="trnIdSfxKeyGrp"/>
			<element type="char" name="buyCod"/>
			<element type="char" name="dateLstUpdDat" size="18"/>
		</sequence>
	</complexType>
	<complexType name="optRejTakUpTrnRequestT">
		<sequence>
			<element type="dataHeaderT" name="header"/>
			<element type="optBscRejTakUpTrnRequestT" name="basic"/>
		</sequence>
	</complexType>
	<complexType name="optBscRejTakUpTrnResponseT">
		<sequence>
			<element type="char" name="gutSts"/>
			<element type="char" name="dateLstUpdDat" size="18"/>
		</sequence>
	</complexType>
	<complexType name="optRejTakUpTrnResponseT">
		<sequence>
			<element type="dataHeaderT" name="header"/>
			<element type="optBscRejTakUpTrnResponseT" name="basic"/>
		</sequence>
	</complexType>
</struct>
